c2dn/__init__.py
c2dn/cli.py
c2dn/client.py
c2dn/errors.py
c2dn/utils.py
c2dn-0.1.5.dist-info/LICENSE
c2dn-0.1.5.dist-info/METADATA
c2dn-0.1.5.dist-info/WHEEL
c2dn-0.1.5.dist-info/entry_points.txt
c2dn-0.1.5.dist-info/top_level.txt
c2dn-0.1.5.dist-info/RECORD
