Metadata-Version: 2.1
Name: c2dn
Version: 0.1.5
Summary: Clip2Net Downloader
Home-page: https://github.com/alexdoesh/c2dn
Author: Alex Doe
Author-email: alex@doe.sh
License-File: LICENSE
Requires-Dist: requests (==2.28.2)
Requires-Dist: lxml (==4.9.2)
Requires-Dist: tqdm (==4.64.1)
